LICENSE
MANIFEST.in
README.md
setup.py
./requirements.txt
infrastack/__init__.py
infrastack.egg-info/PKG-INFO
infrastack.egg-info/SOURCES.txt
infrastack.egg-info/dependency_links.txt
infrastack.egg-info/not-zip-safe
infrastack.egg-info/requires.txt
infrastack.egg-info/top_level.txt
infrastack/flask/__init__.py
infrastack/flask/flask_instrumentation.py
infrastack/logs/__init__.py
infrastack/logs/log_handler.py
infrastack/tracer/__init__.py
infrastack/tracer/create_tracer.py