Metadata-Version: 2.1
Name: infrastack
Version: 0.2.0
Summary: Empowering Developers with AI-First DevTools
Home-page: https://github.com/infrastackai/python-sdk
Author: Infrastack AI
Author-email: info@infrastack.ai
License: MIT
Platform: UNKNOWN
Requires-Python: >= 3
